wilddog/__init__.py
wilddog/cli.py
wilddog/config.py
wilddog/types.py
wilddog/alembic/__init__.py
wilddog/alembic/env.py
wilddog/alembic/migration.py
wilddog/alembic/script.py.mako
wilddog/alembic/versions/3ef406d9f379_.py
wilddog/alembic/versions/6008fc1fee35_extend_models_to_support_attributes_and_.py
wilddog/alembic/versions/__init__.py
wilddog/api/__init__.py
wilddog/api/app.py
wilddog/api/exceptions.py
wilddog/api/response.py
wilddog/api/metadata/__init__.py
wilddog/api/metadata/service.py
wilddog/api/metadata/v0.py
wilddog/api/projects/__init__.py
wilddog/api/projects/service.py
wilddog/api/projects/v0.py
wilddog/models/__init__.py
wilddog/models/base.py
wilddog/models/metadata.py
wilddog/models/transactions.py
wilddog/models/validators.py
wilddog-0.1.0rc3.dist-info/LICENSE
wilddog-0.1.0rc3.dist-info/METADATA
wilddog-0.1.0rc3.dist-info/WHEEL
wilddog-0.1.0rc3.dist-info/entry_points.txt
wilddog-0.1.0rc3.dist-info/top_level.txt
wilddog-0.1.0rc3.dist-info/RECORD
