Metadata-Version: 2.1
Name: wilddog
Version: 0.1.0rc3
Summary: A generic NFT metadata service
Home-page: https://github.com/Neemworks/wilddog
Author: Neemworks Team
Author-email: wilddog@nimworks.com
License: Apache 2.0
Project-URL: Bug Tracker, https://github.com/Neemworks/wilddog/issues
Keywords: NFT,metadata
Platform: UNKNOWN
Classifier: Development Status :: 4 - Beta
Classifier: Programming Language :: Python :: 3
Classifier: License :: OSI Approved :: Apache Software License
Classifier: Operating System :: MacOS :: MacOS X
Classifier: Operating System :: POSIX
Classifier: Operating System :: POSIX :: BSD
Classifier: Operating System :: POSIX :: Linux
Classifier: Operating System :: Microsoft :: Windows
Classifier: Framework :: Flask
Classifier: Intended Audience :: Developers
Classifier: Natural Language :: English
Requires-Python: >=3.9
License-File: LICENSE
Requires-Dist: alembic
Requires-Dist: attrs
Requires-Dist: click
Requires-Dist: flask
Requires-Dist: PyYaml
Requires-Dist: psycopg2
Requires-Dist: sqlalchemy[mypy]
Requires-Dist: tomli
Requires-Dist: waitress
Provides-Extra: changelog
Requires-Dist: towncrier ; extra == 'changelog'
Provides-Extra: dev
Requires-Dist: coverage[toml] ; extra == 'dev'
Requires-Dist: pytest ; extra == 'dev'
Requires-Dist: pytest-cov ; extra == 'dev'
Requires-Dist: pytest-flask ; extra == 'dev'
Provides-Extra: docs
Requires-Dist: sphinx ; extra == 'docs'
Requires-Dist: sphinx-rtd-theme ; extra == 'docs'
Requires-Dist: sphinxcontrib-napoleon ; extra == 'docs'
Provides-Extra: lint
Requires-Dist: mypy ; extra == 'lint'
Requires-Dist: pre-commit ; extra == 'lint'
